LICENSE
MANIFEST.in
README.md
pyproject.toml
setup.py
src/C_star_grid.cpython-312-x86_64-linux-gnu.so
src/antaress/__init__.py
src/antaress.egg-info/PKG-INFO
src/antaress.egg-info/SOURCES.txt
src/antaress.egg-info/dependency_links.txt
src/antaress.egg-info/entry_points.txt
src/antaress.egg-info/requires.txt
src/antaress.egg-info/top_level.txt
src/antaress/ANTARESS_analysis/ANTARESS_ana_comm.py
src/antaress/ANTARESS_analysis/ANTARESS_inst_resp.py
src/antaress/ANTARESS_analysis/ANTARESS_joined_atm.py
src/antaress/ANTARESS_analysis/ANTARESS_joined_star.py
src/antaress/ANTARESS_analysis/ANTARESS_model_prof.py
src/antaress/ANTARESS_analysis/__init__.py
src/antaress/ANTARESS_analysis/C_grid/C_star_grid.c
src/antaress/ANTARESS_analysis/C_grid/C_star_grid.so
src/antaress/ANTARESS_analysis/C_grid/build/lib.macosx-10.9-x86_64-cpython-311/Gauss_star_grid.cpython-311-darwin.so
src/antaress/ANTARESS_analysis/C_grid/build/temp.macosx-10.9-x86_64-cpython-311/Gauss_star_grid.o
src/antaress/ANTARESS_conversions/ANTARESS_binning.py
src/antaress/ANTARESS_conversions/ANTARESS_conv.py
src/antaress/ANTARESS_conversions/ANTARESS_masks_gen.py
src/antaress/ANTARESS_conversions/ANTARESS_sp_cont.py
src/antaress/ANTARESS_conversions/__init__.py
src/antaress/ANTARESS_conversions/KitCat/KitCat_main.py
src/antaress/ANTARESS_conversions/KitCat/Kitcat_classes.py
src/antaress/ANTARESS_conversions/KitCat/Kitcat_functions.py
src/antaress/ANTARESS_conversions/KitCat/calculate_RV_line_by_line3.cpython-311-darwin.so
src/antaress/ANTARESS_conversions/KitCat/calculate_RV_line_by_line_Bouchy.c
src/antaress/ANTARESS_conversions/KitCat/setup_lbl_fit.py
src/antaress/ANTARESS_conversions/KitCat/build/lib.macosx-10.9-x86_64-cpython-311/calculate_RV_line_by_line3.cpython-311-darwin.so
src/antaress/ANTARESS_conversions/KitCat/build/temp.macosx-10.9-x86_64-cpython-311/calculate_RV_line_by_line_Bouchy.o
src/antaress/ANTARESS_corrections/ANTARESS_calib.py
src/antaress/ANTARESS_corrections/ANTARESS_detrend.py
src/antaress/ANTARESS_corrections/ANTARESS_flux_balance.py
src/antaress/ANTARESS_corrections/ANTARESS_interferences.py
src/antaress/ANTARESS_corrections/ANTARESS_peaks.py
src/antaress/ANTARESS_corrections/ANTARESS_sp_reduc.py
