Metadata-Version: 2.4
Name: antaress
Version: 1.1.7
Summary: High-resolution spectroscopy pipeline
Author-email: Vincent Bourrier <vincent.bourrier@unige.ch>
Project-URL: Homepage, https://gitlab.unige.ch/spice_dune/ANTARESS
Project-URL: Issues, https://gitlab.unige.ch/spice_dune/ANTARESS/-/issues
Classifier: Programming Language :: Python :: 3
Classifier: License :: OSI Approved :: GNU Lesser General Public License v3 or later (LGPLv3+)
Classifier: Operating System :: OS Independent
Requires-Python: >=3.8
License-File: LICENSE
Requires-Dist: numpy>=1.16
Requires-Dist: scipy
Requires-Dist: matplotlib
Requires-Dist: imageio
Requires-Dist: pathos
Requires-Dist: mpmath
Requires-Dist: lmfit
Requires-Dist: batman-package
Requires-Dist: astropy
Requires-Dist: emcee
Requires-Dist: pandas
Requires-Dist: dace-query
Requires-Dist: statsmodels
Requires-Dist: bindensity
Requires-Dist: PyAstronomy
Requires-Dist: pysme-astro
Requires-Dist: jupyterlab
Requires-Dist: arviz
Requires-Dist: dynesty
Dynamic: license-file
